[{"s":"fp27573989","o":"Free People","u":"women","a":"dresses","n":"Butterfly V Dress","l":"http:\/\/www.freepeople.com\/clothes-dresses\/butterfly-v-dress\/_\/PRODUCTOPTIONIDS\/3EAEB383-8755-414F-9834-D356F32B8065\/","i":"http:\/\/images3.freepeople.com\/is\/image\/FreePeople\/27573989_004_a?$browse-lt$","p":"128.00","rc":"0","cc":"221","sl":"free-people-butterfly-v-dress"},{"s":"ll2713033","o":"Lord & Taylor","u":"women","a":"Sweaters & Sweatshirts","n":"Lace-Up Poncho Top","l":"http:\/\/www.lordandtaylor.com\/webapp\/wcs\/stores\/servlet\/en\/lord-and-taylor\/womens-apparel\/wa-sweaters\/lace-up-poncho-top","i":"\/\/s7d9.scene7.com\/is\/image\/\/LordandTaylor\/\/888235102696_main?$THUMBLARGE$","p":"110.00","rc":"0","cc":"133","sl":"lord-and-taylor-lace-up-poncho-top"},{"s":"g969314002","o":"Banana Republic","u":"women","a":"shirts","n":"Silk Utility Blouse","l":"http:\/\/bananarepublic.gap.com\/browse\/product.do?cid=5037&vid=1&pid=969314002","i":"http:\/\/www1.assets-gap.com\/webcontent\/0007\/679\/164\/cn7679164.jpg","p":"89.50","rc":"0","cc":"96","sl":"banana-republic-silk-utility-blouse-8"},{"s":"fp20365920","o":"Free People","u":"women","a":"Sweaters & Sweatshirts","n":"Ribbed Up Maxi Cardigan","l":"http:\/\/www.freepeople.com\/clothes-sweaters\/ribbed-up-maxi-cardigan\/_\/PRODUCTOPTIONIDS\/99378B13-7472-425C-A427-4B52BBD62AD7\/","i":"http:\/\/images3.freepeople.com\/is\/image\/FreePeople\/20365920_044_a?$browse-lt$","p":"78.00","rc":"0","cc":"42","sl":"free-people-ribbed-up-maxi-cardigan"},{"s":"g952870002","o":"Old Navy","u":"women","a":"shorts","n":"Women's The Flirt Denim Capris ","l":"http:\/\/oldnavy.gap.com\/browse\/product.do?cid=35158&vid=1&pid=952870002","i":"http:\/\/www3.assets-gap.com\/webcontent\/0007\/595\/341\/cn7595341.jpg","p":"29.94","rc":"0","cc":"72","sl":"old-navy-women-s-the-flirt-denim-capris"},{"s":"l334048","o":"loft","u":"women","a":"outerwear","n":"Knit Open Blazer","l":"http:\/\/www.loft.com\/knit-open-blazer\/334048?colorExplode=false&skuId=15762580&catid=catl000018&productPageType=fullPriceProducts&defaultColor=4632","i":"http:\/\/richmedia.channeladvisor.com\/ImageDelivery\/imageService?profileId=52000653&itemID=334048&swatchID=4632&recipeName=gmd323x335","p":"98.00","rc":"0","cc":"19","sl":"loft-knit-open-blazer"},{"s":"di504274341","o":"Dillards","u":"women","a":"knit","n":"Reba Beverly Lace Embellished Shirt","l":"http:\/\/www.dillards.com\/product\/Reba-Beverly-Lace-Embellished-Shirt_301_-1_301_504274341?df=04179354_zi_periwinkle","i":"http:\/\/dimg.dillards.com\/is\/image\/DillardsZoom\/04179354_zi_periwinkle?$searchCatLarge$","p":"88.00","rc":"0","cc":"169","sl":"dillards-reba-beverly-lace-embellished-shirt"},{"s":"di504378091","o":"Dillards","u":"women","a":"dresses","n":"Cremieux Feya Striped Maxi Dress","l":"http:\/\/www.dillards.com\/product\/Cremieux-Feya-Striped-Maxi-Dress_301_-1_301_504378091?df=04164198_zi_sunrise_mango","i":"http:\/\/dimg.dillards.com\/is\/image\/DillardsZoom\/04164198_zi_sunrise_mango?$searchCatLarge$","p":"129.00","rc":"0","cc":"211","sl":"dillards-cremieux-feya-striped-maxi-dress"},{"s":"m3210","o":"Madewell","u":"women","a":"outerwear","n":"The Jean Vest in Clear Blue","l":"https:\/\/www.madewell.com\/madewell_category\/DENIM\/jackets\/PRDOVR~A3210\/A3210.jsp","i":"https:\/\/s7d9.scene7.com\/is\/image\/madewell\/A3210_DM0623_m?$cat_tn250$","p":"98.00","rc":"0","cc":"49","sl":"madewell-the-jean-vest-in-clear-blue"},{"s":"di504343240","o":"Dillards","u":"women","a":"dresses","n":"Antonio Melani Dinah Crochet Dress","l":"http:\/\/www.dillards.com\/product\/Antonio-Melani-Dinah-Crochet-Dress_301_-1_301_504343240?df=01494293_zi_ivory","i":"http:\/\/dimg.dillards.com\/is\/image\/DillardsZoom\/01494293_zi_ivory?$searchCatLarge$","p":"179.00","rc":"0","cc":"2","sl":"dillards-antonio-melani-dinah-crochet-dress"},{"s":"g949957002","o":"Banana Republic","u":"women","a":"T's & Tops","n":"Snake Print Piped Tee","l":"http:\/\/bananarepublic.gap.com\/browse\/product.do?cid=5040&vid=1&pid=949957002","i":"http:\/\/www1.assets-gap.com\/webcontent\/0007\/303\/193\/cn7303193.jpg","p":"39.50","rc":"0","cc":"0","sl":"banana-republic-snake-print-piped-tee"},{"s":"n3532762","o":"nordstrom","u":"women","a":"skirts","n":"BP. Side Zip Cotton Maxi Skirt (Juniors)","l":"http:\/\/shop.nordstrom.com\/s\/bp-side-zip-cotton-maxi-skirt-juniors\/3532762?origin=category","i":"http:\/\/g.nordstromimage.com\/imagegallery\/store\/product\/Medium\/9\/_8495749.jpg","p":"44.00","rc":"0","cc":"190","sl":"nordstrom-bp-side-zip-cotton-maxi-skirt-juniors"},{"s":"g944089022","o":"Old Navy","u":"women","a":"dresses","n":"Women's Cross-Front Maxi Dresses","l":"http:\/\/oldnavy.gap.com\/browse\/product.do?cid=15292&vid=1&pid=944089022","i":"http:\/\/www1.assets-gap.com\/webcontent\/0007\/308\/980\/cn7308980.jpg","p":"25.00","rc":"0","cc":"232","sl":"old-navy-women-s-cross-front-maxi-dresses-7"},{"s":"ma1219899","o":"Macys","u":"women","a":"Sweaters & Sweatshirts","n":"INC International Concepts Rhinestone-Embellished Scoop-Neck Sweater","l":"http:\/\/www1.macys.com\/shop\/product\/inc-international-concepts-rhinestone-embellished-scoop-neck-sweater?ID=1219899&CategoryID=260","i":"http:\/\/slimages.macys.com\/is\/image\/MCY\/products\/2\/optimized\/1913762_fpx.tif?bgc=255,255,255&wid=164&qlt=90,0&layer=comp&op_sharpen=0&resMode=bicub&op_usm=0.7,1.0,0.5,0&fmt=jpeg","p":"44.99","rc":"0","cc":"108","sl":"macys-inc-international-concepts-rhinestone-embellished-scoop-neck-sweater"},{"s":"bu39157701","o":"Burberry","u":"women","a":"T's & Tops","n":"Striped Cotton Modal Polo Shirt","l":"http:\/\/us.burberry.com\/striped-cotton-modal-polo-shirt-p39157701","i":"http:\/\/assets.burberry.com\/is\/image\/Burberryltd\/cc97da64091cc3e64e683ff70b22be803b2f16a5?$cell_width_retina1$","p":"185.00","rc":"0","cc":"198","sl":"burberry-striped-cotton-modal-polo-shirt"},{"s":"g928933012","o":"Gap","u":"women","a":"jeans","n":"1969 legging jeans","l":"http:\/\/www.gap.com\/browse\/product.do?cid=5664&vid=1&pid=928933012","i":"http:\/\/www1.assets-gap.com\/webcontent\/0007\/390\/191\/cn7390191.jpg","p":"69.95","rc":"0","cc":"74","sl":"gap-1969-legging-jeans-7"},{"s":"bu39233871","o":"Burberry","u":"women","a":"suits","n":"Check Silk Square","l":"http:\/\/us.burberry.com\/check-silk-square-p39233871","i":"http:\/\/assets.burberry.com\/is\/image\/Burberryltd\/4cf87b76e72b28d1fbe7fb6f91e2acc50cbf0870?$cell_width_retina1$","p":"395.00","rc":"0","cc":"9","sl":"burberry-check-silk-square"},{"s":"at321091","o":"Ann Taylor","u":"women","a":"jackets","n":"Tipped Tweed Jacket","l":"http:\/\/www.anntaylor.com\/tipped-tweed-jacket\/321091?colorExplode=false&skuId=15593320&catid=cata000017&productPageType=fullPriceProducts&defaultColor=0255","i":"http:\/\/richmedia.channeladvisor.com\/ImageDelivery\/imageService?profileId=52000652&itemID=321091&swatchID=0255&recipeName=gmd325x400","p":"149.99","rc":"0","cc":"165","sl":"ann-taylor-tipped-tweed-jacket"},{"s":"ho1162719","o":"Hollister","u":"women","a":"jeans","n":"Hollister Boot Jeans","l":"http:\/\/www.hollisterco.com\/shop\/wd\/bettys-boot-jeans\/hollister-boot-jeans-1162719","i":"\/\/anf.scene7.com\/is\/image\/anf\/hol_65262_01_prod1?$category-hol$","p":"59.50","rc":"0","cc":"210","sl":"hollister-hollister-boot-jeans-2"},{"s":"uo31492663","o":"urban outfitters","u":"women","a":"shirts","n":"BDG Crimp Gauze Button-Down Tunic","l":"http:\/\/www.urbanoutfitters.com\/urban\/catalog\/productdetail.jsp?id=31492663&parentid=W_APP_BLOUSES","i":"\/\/images.urbanoutfitters.com\/is\/image\/UrbanOutfitters\/31492663_070_a?$beauty$","p":"39.00","rc":"0","cc":"168","sl":"urban-outfitters-bdg-crimp-gauze-button-down-tunic"},{"s":"g939248012","o":"Old Navy","u":"women","a":"sweatshirts","n":"Women's Lightweight Zip-Hoodies","l":"http:\/\/oldnavy.gap.com\/browse\/product.do?cid=72808&vid=1&pid=939248012","i":"http:\/\/www1.assets-gap.com\/webcontent\/0007\/595\/269\/cn7595269.jpg","p":"22.94","rc":"0","cc":"68","sl":"old-navy-women-s-lightweight-zip-hoodies-2"},{"s":"fp27354851","o":"Free People","u":"women","a":"tops","n":"We The Free Solid Peplum Tee","l":"http:\/\/www.freepeople.com\/clothes-tops\/we-the-free-solid-peplum-tee\/_\/PRODUCTOPTIONIDS\/6AD4E93D-38A6-4B9F-BB17-01F8E9FBC138\/","i":"http:\/\/images2.freepeople.com\/is\/image\/FreePeople\/27354851_041_a?$browse-lt$","p":"58.00","rc":"0","cc":"98","sl":"free-people-we-the-free-solid-peplum-tee"},{"s":"uo30751945","o":"urban outfitters","u":"women","a":"skirts + shorts","n":"One Teaspoon Feather Rose Maxi Skirt","l":"http:\/\/www.urbanoutfitters.com\/urban\/catalog\/productdetail.jsp?id=30751945&parentid=W_APP_BOTTOMS_SHORTS","i":"\/\/images.urbanoutfitters.com\/is\/image\/UrbanOutfitters\/30751945_066_a?$beauty$","p":"129.00","rc":"0","cc":"244","sl":"urban-outfitters-one-teaspoon-feather-rose-maxi-skirt"},{"s":"bcbgWSS2F229-1B1","o":"BCBG","u":"women","a":"pants","n":"Drake Relaxed Trouser","l":"http:\/\/www.bcbg.com\/Drake-Relaxed-Trouser\/WSS2F229-1B1,default,pd.html?dwvar_WSS2F229-1B1_color=1B1&cgid=clothing-by-category-pants","i":"http:\/\/demandware.edgesuite.net\/sits_pod21\/dw\/image\/v2\/AAJT_PRD\/on\/demandware.static\/Sites-BCBG-Site\/Sites-bcbg-master-catalog\/default\/v1396771743951\/images\/WSS2F229_1B1.jpg?sw=174&sh=272","p":"248.00","rc":"0","cc":"211","sl":"bcbg-drake-relaxed-trouser-5"},{"s":"fp31257488","o":"Free People","u":"women","a":"tops","n":"White Sands Crop Top","l":"http:\/\/www.freepeople.com\/clothes-tops\/white-sands-crop-top\/_\/PRODUCTOPTIONIDS\/0B6E9CAD-A8F4-4CCF-8A37-466219F4EA95\/","i":"http:\/\/images2.freepeople.com\/is\/image\/FreePeople\/31257488_001_a?$browse-lt$","p":"48.00","rc":"0","cc":"223","sl":"free-people-white-sands-crop-top"},{"s":"di504173575","o":"Dillards","u":"women","a":"tank tops","n":"Eileen Fisher Linen Sheen Loops Shell Top","l":"http:\/\/www.dillards.com\/product\/Eileen-Fisher-Linen-Sheen-Loops-Shell-Top_301_-1_301_504173575?df=04120238_zi_taupe","i":"http:\/\/dimg.dillards.com\/is\/image\/DillardsZoom\/04120238_zi_taupe?$searchCatLarge$","p":"178.00","rc":"0","cc":"30","sl":"dillards-eileen-fisher-linen-sheen-loops-shell-top"},{"s":"fo2000090998","o":"Forever21","u":"women","a":"skirts","n":"Sleek M-Slit Maxi Skirt","l":"http:\/\/www.forever21.com\/Product\/Product.aspx?BR=f21&Category=bottom_skirt&ProductID=2000090998&VariantID=","i":"http:\/\/www.forever21.com\/images\/cat_main_199\/00090998-01.jpg","p":"15.80","rc":"0","cc":"36","sl":"forever21-sleek-m-slit-maxi-skirt"},{"s":"bcbgWQR1R665-001","o":"BCBG","u":"women","a":"tops","n":"Kenda Sleeveless Asymmetrical Top","l":"http:\/\/www.bcbg.com\/Kenda-Sleeveless-Asymmetrical-Top\/WQR1R665-001,default,pd.html?dwvar_WQR1R665-001_color=001&cgid=clothing-by-category-tops","i":"http:\/\/demandware.edgesuite.net\/sits_pod21\/dw\/image\/v2\/AAJT_PRD\/on\/demandware.static\/Sites-BCBG-Site\/Sites-bcbg-master-catalog\/default\/v1396771743951\/images\/WQR1R665_001.jpg?sw=174&sh=272","p":"158.00","rc":"0","cc":"125","sl":"bcbg-kenda-sleeveless-asymmetrical-top-7"},{"s":"g932955002","o":"Banana Republic","u":"women","a":"Sweaters & Sweatshirts","n":"Ombre Basketweave Open Cardigan","l":"http:\/\/bananarepublic.gap.com\/browse\/product.do?cid=5032&vid=1&pid=932955002","i":"http:\/\/www1.assets-gap.com\/webcontent\/0007\/287\/586\/cn7287586.jpg","p":"120.00","rc":"0","cc":"180","sl":"banana-republic-ombre-basketweave-open-cardigan"},{"s":"a29566247","o":"Anthropologie","u":"Women","a":"T's & Tops","n":"Embroidered Bellis Top","l":"http:\/\/www.anthropologie.com\/anthro\/product\/clothes-blouses\/29566247.jsp","i":"http:\/\/images.anthropologie.com\/is\/image\/Anthropologie\/29566247_001_b?$product410x615$","p":"88.00","rc":"0","cc":"95","sl":"anthropologie-embroidered-bellis-top"},{"s":"n3645813","o":"Nordstrom","u":"Women","a":"Dresses","n":"En Cr\u00e8me Lace Bodice Pleated Skater Dress (Juniors) (Online Only)","l":"http:\/\/shop.nordstrom.com\/s\/en-creme-lace-bodice-pleated-skater-dress-juniors-online-only\/3645813?origin=category","i":"http:\/\/g.nordstromimage.com\/imagegallery\/store\/product\/Medium\/3\/_8565523.jpg","p":"92.00","rc":"0","cc":"111","sl":"nordstrom-en-crme-lace-bodice-pleated-skater-dress-juniors-online-only"},{"s":"g983301002","o":"Piperlime","u":"women","a":"outerwear","n":"Studded Tweed Jacket","l":"http:\/\/piperlime.gap.com\/browse\/product.do?cid=47892&vid=1&pid=983301002","i":"http:\/\/www1.assets-gap.com\/webcontent\/0007\/528\/344\/cn7528344.jpg","p":"836.99","rc":"0","cc":"48","sl":"piperlime-studded-tweed-jacket"},{"s":"fo2002246313","o":"Forever21","u":"women","a":"activewear","n":"Seamless Perforated Workout Tank","l":"http:\/\/www.forever21.com\/Product\/Product.aspx?BR=f21&Category=activewear&ProductID=2002246313&VariantID=","i":"http:\/\/www.forever21.com\/images\/cat_main_199\/02246313-05.jpg","p":"11.80","rc":"0","cc":"149","sl":"forever21-seamless-perforated-workout-tank"},{"s":"di504413869","o":"Dillards","u":"women","a":"pants","n":"M.S.S.P. Relaxed Linen Pants","l":"http:\/\/www.dillards.com\/product\/M.S.S.P.-Relaxed-Linen-Pants_301_-1_301_504413869?df=04186749_zi_beige","i":"http:\/\/dimg.dillards.com\/is\/image\/DillardsZoom\/04186749_zi_beige?$searchCatLarge$","p":"78.00","rc":"0","cc":"60","sl":"dillards-m-s-s-p-relaxed-linen-pants"},{"s":"g674840682","o":"Gap","u":"Women","a":"T's & Tops","n":"Pure Body long-sleeve crew T","l":"http:\/\/www.gap.com\/browse\/product.do?cid=17076&vid=1&pid=674840682","i":"http:\/\/www1.assets-gap.com\/webcontent\/0006\/645\/004\/cn6645004.jpg","p":"19.99","rc":"0","cc":"72","sl":"gap-pure-body-long-sleeve-crew-t"},{"s":"ll2748114","o":"Lord & Taylor","u":"women","a":"dresses","n":"Zipper Back Sheath Dress","l":"http:\/\/www.lordandtaylor.com\/webapp\/wcs\/stores\/servlet\/en\/lord-and-taylor\/womens-apparel\/wa-dresses\/zipper-back-sheath-dress","i":"\/\/s7d9.scene7.com\/is\/image\/\/LordandTaylor\/\/700289813819_main?$THUMBLARGE$","p":"95.99","rc":"0","cc":"207","sl":"lord-and-taylor-zipper-back-sheath-dress"},{"s":"fo2000123299","o":"Forever21","u":"women","a":"pants","n":"Minimalist Woven Trousers","l":"http:\/\/www.forever21.com\/Product\/Product.aspx?BR=f21&Category=bottom_pants&ProductID=2000123299&VariantID=","i":"http:\/\/www.forever21.com\/images\/cat_main_199\/00123299-01.jpg","p":"22.80","rc":"0","cc":"83","sl":"forever21-minimalist-woven-trousers"},{"s":"n3707107","o":"nordstrom","u":"women","a":"tops","n":"Topshop Unique Star Print Silk Camisole","l":"http:\/\/shop.nordstrom.com\/s\/topshop-unique-star-print-silk-camisole\/3707107?origin=category","i":"http:\/\/g.nordstromimage.com\/imagegallery\/store\/product\/Medium\/7\/_8786427.jpg","p":"120.00","rc":"0","cc":"142","sl":"nordstrom-topshop-unique-star-print-silk-camisole"},{"s":"g938055062","o":"Old Navy","u":"women","a":"Sweaters & Sweatshirts","n":"Women's Crew Sweatshirts","l":"http:\/\/oldnavy.gap.com\/browse\/product.do?cid=72808&vid=1&pid=938055062","i":"http:\/\/www3.assets-gap.com\/webcontent\/0007\/355\/550\/cn7355550.jpg","p":"9.97","rc":"0","cc":"13","sl":"old-navy-women-s-crew-sweatshirts-2"},{"s":"uo31818347","o":"Urban Outfitters","u":"women","a":"shirts","n":"Kimchi Blue Lace-Trim Silk Cami","l":"http:\/\/www.urbanoutfitters.com\/urban\/catalog\/productdetail.jsp?id=31818347&parentid=W_APP_BLOUSES","i":"\/\/images.urbanoutfitters.com\/is\/image\/UrbanOutfitters\/31818347_067_a?$beauty$","p":"49.00","rc":"0","cc":"35","sl":"urban-outfitters-kimchi-blue-lace-trim-silk-cami"},{"s":"tb50001210","o":"Tory Burch","u":"women","a":"denim","n":"LEGGING JEAN IN RINSE","l":"http:\/\/www.toryburch.com\/legging-jean-in-rinse\/50001210.html?dwvar_50001210_color=473&start=7&cgid=clothing-denim","i":"http:\/\/s7d5.scene7.com\/is\/image\/ToryBurchLLC\/TB_50001210_473?$trb_grid_md$","p":"185.00","rc":"0","cc":"175","sl":"tory-burch-legging-jean-in-rinse"},{"s":"nmprod166050258","o":"Neiman Marcus","u":"women","a":"tunics","n":"Stud-Neck Silk Tunic","l":"http:\/\/www.neimanmarcus.com\/Michael-Kors-Stud-Neck-Silk-Tunic-Tunics\/prod166050258_cat42160745__\/p.prod?icid=&searchType=EndecaDrivenCat&rte=%252Fcategory.jsp%253FitemId%253Dcat42160745%2526pageSize%253D30%2526No%253D0%2526refinements%253D&eItemId=prod166050258&cmCat=product","i":"http:\/\/images.neimanmarcus.com\/ca\/1\/product_assets\/B\/2\/F\/Q\/1\/NMB2FQ1_mi.jpg","p":"1495.00","rc":"0","cc":"153","sl":"neiman-marcus-stud-neck-silk-tunic"},{"s":"m4055","o":"Madewell","u":"women","a":"t shirts","n":"Ref Sweatshirt","l":"https:\/\/www.madewell.com\/madewell_category\/TEESANDMORE\/sweatshirtsandmore\/PRDOVR~A4055\/A4055.jsp","i":"https:\/\/s7d9.scene7.com\/is\/image\/madewell\/A4055_KS7803_m?$cat_tn250$","p":"95.50","rc":"0","cc":"214","sl":"madewell-ref-sweatshirt"},{"s":"g952694012","o":"Old Navy","u":"women","a":"shirts","n":"Women's Gauze Boho Tops","l":"http:\/\/oldnavy.gap.com\/browse\/product.do?cid=72087&vid=1&pid=952694012","i":"http:\/\/www1.assets-gap.com\/webcontent\/0007\/675\/827\/cn7675827.jpg","p":"26.94","rc":"0","cc":"113","sl":"old-navy-women-s-gauze-boho-tops"},{"s":"g605134002","o":"Gap","u":"women","a":"T's & Tops","n":"Fluid pocket T","l":"http:\/\/www.gap.com\/browse\/product.do?cid=17076&vid=1&pid=605134002","i":"http:\/\/www1.assets-gap.com\/webcontent\/0006\/612\/888\/cn6612888.jpg","p":"14.99","rc":"0","cc":"68","sl":"gap-fluid-pocket-t"},{"s":"cu10030005221","o":"Cusp","u":"women","a":"Sweaters & Sweatshirts","n":"Brushed Colorblock Asymmetric Sweater","l":"http:\/\/www.cusp.com\/product.jsp?rte=%252Fcategory.jsp%253FitemId%253Dcat2280023%2526pageSize%253D1000%2526No%253D0%2526refinements%253D&seoDesigner=Helmut+Lang&icid=&seoCategory=Sweaters&parentId=cat2280023&eItemId=prod10030005&seoProduct=Brushed+Colorblock+Asymmetric+Sweater&searchType=EndecaDriven","i":"http:\/\/images.cusp.com\/ca\/1\/product_assets\/T\/7\/L\/0\/8\/CUT7L08_mi.jpg","p":"221.00","rc":"0","cc":"47","sl":"cusp-brushed-colorblock-asymmetric-sweater"},{"s":"at324118","o":"Ann Taylor","u":"Women","a":"Sweaters & Sweatshirts","n":"Contrast Trim Zip Front Sweater Jacket","l":"http:\/\/www.anntaylor.com\/contrast-trim-zip-front-sweater-jacket\/324118?colorExplode=false&skuId=15040022&catid=cata000017&productPageType=fullPriceProducts&defaultColor=6600","i":"http:\/\/richmedia.channeladvisor.com\/ImageDelivery\/imageService?profileId=52000652&itemID=324118&swatchID=6600&recipeName=gmd325x400","p":"109.99","rc":"0","cc":"239","sl":"ann-taylor-contrast-trim-zip-front-sweater-jacket"},{"s":"aarsa0301w","o":"American Apparel","u":"Women","a":"Sweaters & Sweatshirts","n":"Unisex Dolman Sleeve Hoodie","l":"http:\/\/store.americanapparel.net\/product\/?productId=rsa0301w","i":"http:\/\/s7d9.scene7.com\/is\/image\/AmericanApparel\/rsa0301w_black?defaultImage=\/notavail&$ProductThumbnail$","p":"29.00","rc":"0","cc":"17","sl":"american-apparel-unisex-dolman-sleeve-hoodie"},{"s":"aarsapp400w","o":"American Apparel","u":"Women","a":"Outerwear","n":"Unisex Perfect Vest ","l":"http:\/\/store.americanapparel.net\/unisex-perfect-vest-_rsapp400w","i":"http:\/\/s7d9.scene7.com\/is\/image\/AmericanApparel\/rsapp400w_red?defaultImage=\/notavail&$ProductThumbnail$","p":"71.40","rc":"0","cc":"42","sl":"american-apparel-unisex-perfect-vest"},{"s":"di504341668","o":"Dillards","u":"women","a":"skirts","n":"Antonio Melani Zeina Pencil Skirt","l":"http:\/\/www.dillards.com\/product\/Antonio-Melani-Zeina-Pencil-Skirt_301_-1_301_504341668?df=04193407_zi_chili","i":"http:\/\/dimg.dillards.com\/is\/image\/DillardsZoom\/04193407_zi_chili?$searchCatLarge$","p":"99.00","rc":"0","cc":"208","sl":"dillards-antonio-melani-zeina-pencil-skirt"}]