[{"s":"g268517012","o":"Athleta","u":"women","a":"capris","n":"Bettona 2 in 1 Skirt Capri","l":"http:\/\/athleta.gap.com\/browse\/product.do?cid=46804&vid=1&pid=268517012","i":"http:\/\/www1.assets-gap.com\/webcontent\/0005\/291\/447\/cn5291447.jpg","p":"79.00","rc":"0","cc":"0","sl":"athleta-bettona-2-in-1-skirt-capri"},{"s":"g605819052","o":"Gap","u":"women","a":"T's & Tops","n":"Waffle knit baseball T","l":"http:\/\/www.gap.com\/browse\/product.do?cid=17076&vid=1&pid=605819052","i":"http:\/\/www1.assets-gap.com\/webcontent\/0006\/863\/871\/cn6863871.jpg","p":"9.99","rc":"0","cc":"0","sl":"gap-waffle-knit-baseball-t-4"},{"s":"lll3516335","o":"Lululemon","u":"Women","a":"Leggings","n":"Street To Studio Crop *No Liner","l":"http:\/\/shop.lululemon.com\/products\/clothes-accessories\/cropped-pants\/Street-To-Studio-Crop?cc=0010&skuId=3516335&catId=cropped-pants","i":"http:\/\/images.lululemon.com\/is\/image\/lululemon\/LW6932S_0010_1?$cdp_thumb$","p":"88.00","rc":"0","cc":"0","sl":"lululemon-street-to-studio-crop-no-liner-3"},{"s":"g100436002","o":"Piperlime","u":"women","a":"tops","n":"Lex Silk Shirred Popover Top","l":"http:\/\/piperlime.gap.com\/browse\/product.do?cid=64474&vid=1&pid=100436002","i":"http:\/\/www1.assets-gap.com\/webcontent\/0007\/631\/955\/cn7631955.jpg","p":"79.00","rc":"0","cc":"0","sl":"piperlime-lex-silk-shirred-popover-top-2"},{"s":"a29108131","o":"Anthropologie","u":"Women","a":"Pants","n":"Twill Moto  Leggings","l":"http:\/\/www.anthropologie.com\/anthro\/product\/clothes-pants\/29108131.jsp","i":"http:\/\/images.anthropologie.com\/is\/image\/Anthropologie\/29108131_005_b?$product410x615$","p":"88.00","rc":"0","cc":"0","sl":"anthropologie-twill-moto-leggings"},{"s":"ho1950085","o":"Hollister","u":"women","a":"Sweaters & Sweatshirts","n":"Summerland Shine Hoodie","l":"http:\/\/www.hollisterco.com\/shop\/us\/bettys-pullover-hoodies-and-sweatshirts\/summerland-hoodie-1950085","i":"\/\/anf.scene7.com\/is\/image\/anf\/hol_71350_01_prod1?$category-hol$","p":"44.95","rc":"0","cc":"0","sl":"hollister-summerland-shine-hoodie-2"},{"s":"at320539","o":"Ann Taylor","u":"women","a":"shirts","n":"Draped Sheer Sleeve Top","l":"http:\/\/www.anntaylor.com\/draped-sheer-sleeve-top\/320539?colorExplode=false&skuId=15440129&catid=cat70008&productPageType=fullPriceProducts&defaultColor=1606","i":"http:\/\/richmedia.channeladvisor.com\/ImageDelivery\/imageService?profileId=52000652&itemID=320539&swatchID=1606&recipeName=gmd325x400","p":"49.99","rc":"0","cc":"0","sl":"ann-taylor-draped-sheer-sleeve-top"},{"s":"g950121032","o":"Banana Republic","u":"women","a":"T's & Tops","n":"Heritage Linen Roll-Sleeve Top","l":"http:\/\/bananarepublic.gap.com\/browse\/product.do?cid=5040&vid=1&pid=950121032","i":"http:\/\/www3.assets-gap.com\/webcontent\/0007\/315\/460\/cn7315460.jpg","p":"45.00","rc":"0","cc":"0","sl":"banana-republic-heritage-linen-roll-sleeve-top-4"},{"s":"cu7080037104","o":"Cusp","u":"women","a":"jeans","n":"The Legacy Skinny Jeans, Coated Black","l":"http:\/\/www.cusp.com\/product.jsp?rte=%252Fcategory.jsp%253FitemId%253Dcat2280013%2526pageSize%253D1000%2526No%253D0%2526refinements%253D&seoDesigner=Rich+and+Skinny&icid=&seoCategory=Denim&parentId=cat2280013&eItemId=prod7080037&seoProduct=The+Legacy+Skinny+Jeans%2C+Coated+Black&searchType=EndecaDriv","i":"http:\/\/images.cusp.com\/ca\/1\/product_assets\/T\/7\/0\/P\/U\/CUT70PU_mi.jpg","p":"53.00","rc":"0","cc":"0","sl":"cusp-the-legacy-skinny-jeans-coated-black"},{"s":"cu7500050485","o":"Cusp","u":"women","a":"shirts","n":"Nexa V-Neck Combo Top","l":"http:\/\/www.cusp.com\/product.jsp?rte=%252Fcategory.jsp%253FitemId%253Dcat2280017%2526pageSize%253D1000%2526No%253D0%2526refinements%253D&seoDesigner=HELMUT+Helmut+Lang&icid=&seoCategory=Tops&parentId=cat2280017&eItemId=prod7500050&seoProduct=Nexa+V-Neck+Combo+Top&searchType=EndecaDrivenCat&cmCat=prod","i":"http:\/\/images.cusp.com\/ca\/1\/product_assets\/T\/7\/3\/9\/W\/CUT739W_mi.jpg","p":"195.00","rc":"0","cc":"0","sl":"cusp-nexa-v-neck-combo-top"},{"s":"cu674001386","o":"Cusp","u":"women","a":"jeans","n":"The Absolute Leggings, Lastcall","l":"http:\/\/www.cusp.com\/product.jsp?rte=%252Fcategory.jsp%253FitemId%253Dcat2280013%2526pageSize%253D1000%2526No%253D0%2526refinements%253D&seoDesigner=AG+Adriano+Goldschmied&icid=&seoCategory=Denim&parentId=cat2280013&eItemId=prod6740013&seoProduct=The+Absolute+Leggings%2C+Lastcall&searchType=EndecaDri","i":"http:\/\/images.cusp.com\/ca\/1\/product_assets\/T\/6\/X\/Z\/2\/CUT6XZ2_mi.jpg","p":"178.00","rc":"0","cc":"0","sl":"cusp-the-absolute-leggings-lastcall"},{"s":"n3714810","o":"nordstrom","u":"women","a":"jeans","n":"Topshop Moto 'Joni' High Rise Skinny Jeans (Light Denim)","l":"http:\/\/shop.nordstrom.com\/s\/topshop-moto-joni-high-rise-skinny-jeans-light-denim\/3714810?origin=category","i":"http:\/\/g.nordstromimage.com\/imagegallery\/store\/product\/Medium\/14\/_8826234.jpg","p":"65.00","rc":"0","cc":"0","sl":"nordstrom-topshop-moto-joni-high-rise-skinny-jeans-light-denim"},{"s":"di504341659","o":"Dillards","u":"women","a":"suits","n":"Antonio Melani Apple Pintucked-Sleeve Dress","l":"http:\/\/www.dillards.com\/product\/Antonio-Melani-Apple-PintuckedSleeve-Dress_301_-1_301_504341659?df=04193397_zi_chili","i":"http:\/\/dimg.dillards.com\/is\/image\/DillardsZoom\/04193397_zi_chili?$searchCatLarge$","p":"159.00","rc":"0","cc":"0","sl":"dillards-antonio-melani-apple-pintucked-sleeve-dress"},{"s":"ts13797349","o":"Top Shop","u":"women","a":"jeans","n":"MOTO  New Wash Black Baxter Jeans","l":"http:\/\/www.topshop.com\/en\/tsuk\/product\/clothing-427\/jeans-446\/moto-new-wash-black-baxter-jeans-2663035?bi=1&ps=20","i":"http:\/\/media.topshop.com\/wcsstore\/TopShop\/images\/catalog\/02S16FWBK_thumb.jpg","p":"40.00","rc":"0","cc":"0","sl":"top-shop-moto-new-wash-black-baxter-jeans"},{"s":"bcbgNPY1O732-B4P","o":"BCBG","u":"women","a":"tops","n":"Jonesy Boatneck Loose-Draped Top","l":"http:\/\/www.bcbg.com\/Jonesy-Boatneck-Loose-Draped-Top\/NPY1O732-B4P,default,pd.html?dwvar_NPY1O732-B4P_color=B4P&cgid=clothing-by-category-tops","i":"http:\/\/demandware.edgesuite.net\/sits_pod21\/dw\/image\/v2\/AAJT_PRD\/on\/demandware.static\/Sites-BCBG-Site\/Sites-bcbg-master-catalog\/default\/v1393319199646\/images\/NPY1O732_B4P.jpg?sw=174&sh=272","p":"98.00","rc":"0","cc":"0"},{"s":"ll2737237","o":"Lord & Taylor","u":"women","a":"suits","n":"Plus Two-Piece Karena Pants Suit","l":"http:\/\/www.lordandtaylor.com\/webapp\/wcs\/stores\/servlet\/en\/lord-and-taylor\/womens-apparel\/wa-suiting\/plus-two-piece-karena-pants-suit","i":"\/\/s7d9.scene7.com\/is\/image\/\/LordandTaylor\/\/822992329637_main?$THUMBLARGE$","p":"192.00","rc":"0","cc":"0","sl":"lord-and-taylor-plus-two-piece-karena-pants-suit"},{"s":"g777790002","o":"Piperlime","u":"women","a":"loungewear","n":"Full Length Legging","l":"http:\/\/piperlime.gap.com\/browse\/product.do?cid=78153&vid=1&pid=777790002","i":"http:\/\/www1.assets-gap.com\/webcontent\/0004\/876\/846\/cn4876846.jpg","p":"48.00","rc":"0","cc":"0","sl":"piperlime-full-length-legging"},{"s":"lll3514329","o":"Lululemon","u":"Women","a":"Pants","n":"Groove Pant (Regular)","l":"http:\/\/shop.lululemon.com\/products\/clothes-accessories\/pants-yoga\/Groove-Pant-Slim-Regular?cc=11648&skuId=3514329&catId=pants-yoga","i":"http:\/\/images.lululemon.com\/is\/image\/lululemon\/LW5952R_011648_1?$cdp_thumb$","p":"98.00","rc":"0","cc":"0","sl":"lululemon-groove-pant-regular"},{"s":"a4130232790100","o":"anthropologie","u":"women","a":"dresses","n":"Geojacquard Dress","l":"http:\/\/www.anthropologie.com\/anthro\/product\/clothes-dresses\/4130232790100.jsp","i":"\/anthro\/images\/blank.gif","p":"168.00","rc":"0","cc":"0","sl":"anthropologie-geojacquard-dress"},{"s":"g953909002","o":"Old Navy","u":"women","a":"dresses","n":"Women's Striped Waisted Chambray Dresses","l":"http:\/\/oldnavy.gap.com\/browse\/product.do?cid=15292&vid=1&pid=953909002","i":"http:\/\/www3.assets-gap.com\/webcontent\/0007\/474\/293\/cn7474293.jpg","p":"25.00","rc":"0","cc":"0","sl":"old-navy-women-s-striped-waisted-chambray-dresses"},{"s":"bu39088921","o":"Burberry","u":"women","a":"coats","n":"Funnel Collar Parka with Warmer","l":"http:\/\/us.burberry.com\/funnel-collar-parka-with-warmer-p39088921","i":"http:\/\/assets.burberry.com\/is\/image\/Burberryltd\/9c359ba9fa20d04858854d562566ade8813f0cd9?$cell_width_retina1$","p":"1295.00","rc":"0","cc":"0","sl":"burberry-funnel-collar-parka-with-warmer"},{"s":"jp5003180196","o":"JCPenny","u":"women","a":"jackets","n":"9 & Co.\u00ae 2-Button Notch-Collar Jacket","l":"http:\/\/www.jcpenney.com\/wear-to-work\/9-co-2-button-notch-collar-jacket\/prod.jump?ppId=pp5003180196&catId=cat100260321&deptId=dept20000013&Nao=96&pageSize=96&pN=1&colorizedImg=DP0830201317033044M.tif","i":"http:\/\/zoom.jcpenney.com\/is\/image\/DP0830201317033044M.tif?wid=180&hei=180&op_usm=.4,.8,0,0&resmode=sharp2&op_usm=1.5,.8,0,0&resmode=sharp","p":"49.99","rc":"0","cc":"0","sl":"jcpenny-9-co-2-button-notch-collar-jacket"},{"s":"b729552","o":"bloomingdales","u":"women","a":"outerwear","n":"Canada Goose Down Jacket - Hybridge Lightweight","l":"http:\/\/www1.bloomingdales.com\/shop\/product\/canada-goose-down-jacket-hybridge-lightweight?ID=729552&CategoryID=1001520#fn%3Dspp%3D20","i":"http:\/\/images.bloomingdales.com\/is\/image\/BLM\/products\/5\/optimized\/8331695_fpx.tif","p":"575.00","rc":"0","cc":"0","sl":"bloomingdales-canada-goose-down-jacket-hybridge-lightweight"},{"s":"lll3488374","o":"Lululemon","u":"Women","a":"Tank Tops","n":"Run: Swiftly Tech Racerback *Shortcut","l":"http:\/\/shop.lululemon.com\/products\/clothes-accessories\/tanks-no-support\/Run-Swiftly-Tech-Racerback-Shortcut?cc=9906&skuId=3488374&catId=tanks-no-support","i":"http:\/\/images.lululemon.com\/is\/image\/lululemon\/LW1960S_9906_1?$cdp_thumb$","p":"48.00","rc":"0","cc":"0","sl":"lululemon-run-swiftly-tech-racerback-shortcut-3"},{"s":"fp31633704","o":"Free People","u":"women","a":"tops","n":"Delphi Tank","l":"http:\/\/www.freepeople.com\/clothes-tops\/delphi-tank\/_\/PRODUCTOPTIONIDS\/0B6E9CAD-A8F4-4CCF-8A37-466219F4EA95\/","i":"http:\/\/images3.freepeople.com\/is\/image\/FreePeople\/31633704_001_a?$browse-lt$","p":"70.00","rc":"0","cc":"0","sl":"free-people-delphi-tank"},{"s":"uo31293244","o":"urban outfitters","u":"women","a":"tops","n":"Sparkle & Fade Alexa Dolman Tee","l":"http:\/\/www.urbanoutfitters.com\/urban\/catalog\/productdetail.jsp?id=31293244&parentid=W_TOPS","i":"http:\/\/images.urbanoutfitters.com\/is\/image\/UrbanOutfitters\/31293244_006_a?$beauty$","p":"34.00","rc":"0","cc":"0","sl":"urban-outfitters-sparkle-fade-alexa-dolman-tee"},{"s":"fp29586054","o":"Free People","u":"women","a":"dresses","n":"Embellished Medallion Slip","l":"http:\/\/www.freepeople.com\/clothes-dresses\/embellished-medallion-slip\/_\/PRODUCTOPTIONIDS\/BEE1C344-4601-4985-97DB-EB5BCFE2AD06\/","i":"http:\/\/images3.freepeople.com\/is\/image\/FreePeople\/29586054_040_a?$browse-lt$","p":"98.00","rc":"0","cc":"0","sl":"free-people-embellished-medallion-slip"},{"s":"n3640856","o":"Nordstrom","u":"Women","a":"Dresses","n":"En Cr\u00e8me Strapless Fringe Dress (Juniors)","l":"http:\/\/shop.nordstrom.com\/s\/en-creme-strapless-fringe-dress-juniors\/3640856?origin=category","i":"http:\/\/g.nordstromimage.com\/imagegallery\/store\/product\/Medium\/14\/_8547834.jpg","p":"78.00","rc":"0","cc":"0","sl":"nordstrom-en-crme-strapless-fringe-dress-juniors"},{"s":"g964541002","o":"Athleta","u":"women","a":"capris","n":"Acceleration 2 In 1 Capri","l":"http:\/\/athleta.gap.com\/browse\/product.do?cid=46804&vid=1&pid=964541002","i":"http:\/\/www1.assets-gap.com\/webcontent\/0007\/539\/005\/cn7539005.jpg","p":"74.00","rc":"0","cc":"0","sl":"athleta-acceleration-2-in-1-capri"},{"s":"g929785012","o":"Athleta","u":"women","a":"pants","n":"Cozyup Bettona Boyfriend Pant","l":"http:\/\/athleta.gap.com\/browse\/product.do?cid=46800&vid=1&pid=929785012","i":"http:\/\/www3.assets-gap.com\/webcontent\/0007\/285\/301\/cn7285301.jpg","p":"64.99","rc":"0","cc":"0","sl":"athleta-cozyup-bettona-boyfriend-pant"},{"s":"a29334547","o":"Anthropologie","u":"Women","a":"Sweaters & Sweatshirts","n":"Matinee Cardigan","l":"http:\/\/www.anthropologie.com\/anthro\/product\/clothes-sweaters\/29334547.jsp","i":"http:\/\/images.anthropologie.com\/is\/image\/Anthropologie\/29334547_011_b?$product410x615$","p":"98.00","rc":"0","cc":"0","sl":"anthropologie-matinee-cardigan"},{"s":"a28193951","o":"Anthropologie","u":"Women","a":"T's & Tops","n":"Lottie Pullover","l":"http:\/\/www.anthropologie.com\/anthro\/product\/clothes-blouses\/28193951.jsp","i":"http:\/\/images.anthropologie.com\/is\/image\/Anthropologie\/28193951_004_b?$product410x615$","p":"78.00","rc":"0","cc":"0","sl":"anthropologie-lottie-pullover"},{"s":"jp5003270162","o":"JCPenny","u":"women","a":"dresses","n":"J. Taylor Keyhole Blouson Dress","l":"http:\/\/www.jcpenney.com\/j-taylor-keyhole-blouson-dress-\/prod.jump?ppId=pp5003270162&catId=cat100210008&deptId=dept20000013&Nao=96&pageSize=96&pN=1&colorizedImg=DP0918201317040551M.tif","i":"http:\/\/zoom.jcpenney.com\/is\/image\/DP0918201317040551M.tif?wid=180&hei=180&op_usm=.4,.8,0,0&resmode=sharp2&op_usm=1.5,.8,0,0&resmode=sharp","p":"35.99","rc":"0","cc":"0","sl":"jcpenny-j-taylor-keyhole-blouson-dress"},{"s":"ll2795829","o":"Lord & Taylor","u":"women","a":"sweaters","n":"Zip Front Hooded Sweater","l":"http:\/\/www.lordandtaylor.com\/webapp\/wcs\/stores\/servlet\/en\/lord-and-taylor\/womens-apparel\/wa-sweaters\/zip-front-hooded-sweater","i":"\/\/s7d9.scene7.com\/is\/image\/\/LordandTaylor\/\/885719185886_main?$THUMBLARGE$","p":"99.50","rc":"0","cc":"0","sl":"lord-and-taylor-zip-front-hooded-sweater"},{"s":"g928976022","o":"Gap","u":"women","a":"shirts","n":"Dots & stripes shrunken boyfriend oxford shirt","l":"http:\/\/www.gap.com\/browse\/product.do?cid=34608&vid=1&pid=928976022","i":"http:\/\/www1.assets-gap.com\/webcontent\/0007\/390\/182\/cn7390182.jpg","p":"49.95","rc":"0","cc":"0","sl":"gap-dots-stripes-shrunken-boyfriend-oxford-shirt-2"},{"s":"di503333477","o":"Dillards","u":"women","a":"pants","n":"Calvin Klein Classic Flare-Leg Pants","l":"http:\/\/www.dillards.com\/product\/Calvin-Klein-Classic-FlareLeg-Pants_301_-1_301_503333477?df=03771374_zi_charcoal","i":"http:\/\/dimg.dillards.com\/is\/image\/DillardsZoom\/03771374_zi_charcoal?$searchCatLarge$","p":"59.00","rc":"0","cc":"0","sl":"dillards-calvin-klein-classic-flare-leg-pants"},{"s":"a30120166","o":"Anthropologie","u":"Women","a":"Dresses","n":"Pieced Stripes Column Dress","l":"http:\/\/www.anthropologie.com\/anthro\/product\/clothes-dresses\/30120166.jsp","i":"http:\/\/images.anthropologie.com\/is\/image\/Anthropologie\/30120166_049_b?$product410x615$","p":"178.00","rc":"0","cc":"0","sl":"anthropologie-pieced-stripes-column-dress"},{"s":"g739412092","o":"Athleta","u":"women","a":"shorts","n":"12\" Dipper Short","l":"http:\/\/athleta.gap.com\/browse\/product.do?cid=1005088&vid=1&pid=739412092","i":"http:\/\/www3.assets-gap.com\/webcontent\/0005\/602\/035\/cn5602035.jpg","p":"24.99","rc":"0","cc":"0","sl":"athleta-12-dipper-short"},{"s":"cu6110063851","o":"Cusp","u":"women","a":"dresses","n":"Tahmira Mesh-Sleeve Ponte Dress","l":"http:\/\/www.cusp.com\/product.jsp?rte=%252Fcategory.jsp%253FitemId%253Dcat2240001%2526pageSize%253D1000%2526No%253D0%2526refinements%253D&seoDesigner=Nanette+Lepore&icid=&seoCategory=Dresses&parentId=cat2240001&eItemId=prod6110063&seoProduct=Tahmira+Mesh-Sleeve+Ponte+Dress&searchType=EndecaDrivenCat&c","i":"http:\/\/images.cusp.com\/ca\/1\/product_assets\/T\/6\/T\/Y\/K\/CUT6TYK_mi.jpg","p":"93.00","rc":"0","cc":"0","sl":"cusp-tahmira-mesh-sleeve-ponte-dress"},{"s":"fp29485133","o":"Free People","u":"women","a":"outerwear","n":"Rendered Denim Parka","l":"http:\/\/www.freepeople.com\/clothes-jackets-outerwear\/rendered-denim-parka\/_\/PRODUCTOPTIONIDS\/BEE1C344-4601-4985-97DB-EB5BCFE2AD06\/","i":"http:\/\/images5.freepeople.com\/is\/image\/FreePeople\/29485133_040_a?$browse-lt$","p":"268.00","rc":"0","cc":"0","sl":"free-people-rendered-denim-parka"},{"s":"fp27920875","o":"Free People","u":"women","a":"dresses","n":"First Kiss Dress","l":"http:\/\/www.freepeople.com\/clothes-dresses\/first-kiss-print-maxi-dress\/_\/PRODUCTOPTIONIDS\/1E298FA5-BBCE-4AC8-A5D7-B413F708CF7E\/","i":"http:\/\/images5.freepeople.com\/is\/image\/FreePeople\/27920875_012_a?$browse-lt$","p":"148.00","rc":"0","cc":"0","sl":"free-people-first-kiss-dress"},{"s":"fo2000073528","o":"Forever21","u":"women","a":"jeans","n":"Bold Bleached Jeans","l":"http:\/\/www.forever21.com\/Product\/Product.aspx?BR=f21&Category=bottom_jeans&ProductID=2000073528&VariantID=","i":"http:\/\/www.forever21.com\/images\/cat_main_199\/00073528-02.jpg","p":"22.80","rc":"0","cc":"0","sl":"forever21-bold-bleached-jeans"},{"s":"b980275","o":"bloomingdales","u":"women","a":"pants","n":"MICHAEL Michael Kors Flare Leg Trousers","l":"http:\/\/www1.bloomingdales.com\/shop\/product\/michael-michael-kors-flare-leg-trousers?ID=980275&CategoryID=17566#fn%3Dspp%3D64","i":"http:\/\/images.bloomingdales.com\/is\/image\/BLM\/products\/4\/optimized\/8483854_fpx.tif","p":"99.50","rc":"0","cc":"0","sl":"bloomingdales-michael-michael-kors-flare-leg-trousers"},{"s":"n3514786","o":"Nordstrom","u":"Women","a":"Coats","n":"Bernardo Packable Goose Down Walking Coat","l":"http:\/\/shop.nordstrom.com\/s\/bernardo-packable-goose-down-walking-coat\/3514786?origin=category","i":"http:\/\/g.nordstromimage.com\/imagegallery\/store\/product\/Medium\/18\/_8008738.jpg","p":"178.00","rc":"0","cc":"0","sl":"nordstrom-bernardo-packable-goose-down-walking-coat"},{"s":"fo2000070616","o":"Forever21","u":"women","a":"skirts","n":"Tie-Dye Structured Skirt","l":"http:\/\/www.forever21.com\/Product\/Product.aspx?BR=f21&Category=bottom_skirt&ProductID=2000070616&VariantID=","i":"http:\/\/www.forever21.com\/images\/cat_main_199\/00070616-02.jpg","p":"15.80","rc":"0","cc":"0","sl":"forever21-tie-dye-structured-skirt"},{"s":"a29603081","o":"Anthropologie","u":"Women","a":"Dresses","n":"Mina Jersey Dress","l":"http:\/\/www.anthropologie.com\/anthro\/product\/clothes-dresses\/29603081.jsp","i":"http:\/\/images.anthropologie.com\/is\/image\/Anthropologie\/29603081_020_b?$product410x615$","p":"138.00","rc":"0","cc":"0","sl":"anthropologie-mina-jersey-dress"},{"s":"aacaswtr20363dw","o":"American Apparel","u":"Women","a":"Sweaters & Sweatshirts","n":"Unisex Classic Button Canadian Sweater","l":"http:\/\/store.americanapparel.net\/unisex-classic-button-canadian-sweater_caswtr20363dw","i":"http:\/\/s7d9.scene7.com\/is\/image\/AmericanApparel\/caswtr20363dw_grey?defaultImage=\/notavail&$ProductThumbnail$","p":"238.00","rc":"0","cc":"0","sl":"american-apparel-unisex-classic-button-canadian-sweater"},{"s":"jc07755","o":"J.Crew","u":"Women","a":"Pants","n":"Collection caf\u00e9 capri in tie silk","l":"http:\/\/www.jcrew.com\/womens_category\/pants\/croppedtrousers\/PRDOVR~07755\/07755.jsp","i":"http:\/\/s7.jcrew.com\/is\/image\/jcrew\/07755_WO0982_m?$ary_tn250$","p":"198.00","rc":"0","cc":"0","sl":"j-crew-collection-caf-capri-in-tie-silk"},{"s":"uo30294011","o":"urban outfitters","u":"women","a":"Sweaters & Sweatshirts","n":"Staring At Stars Printed Drape Vest","l":"http:\/\/www.urbanoutfitters.com\/urban\/catalog\/productdetail.jsp?id=30294011&parentid=W_APP_SWEATERS","i":"\/\/images.urbanoutfitters.com\/is\/image\/UrbanOutfitters\/30294011_009_a?$beauty$","p":"59.00","rc":"0","cc":"0","sl":"urban-outfitters-staring-at-stars-printed-drape-vest"},{"s":"n3459292","o":"Nordstrom","u":"Women","a":"Jackets","n":"The North Face 'Aconcagua' Down Jacket","l":"http:\/\/shop.nordstrom.com\/s\/the-north-face-aconcagua-down-jacket\/3459292?origin=category","i":"http:\/\/g.nordstromimage.com\/imagegallery\/store\/product\/Medium\/13\/_8437313.jpg","p":"160.00","rc":"0","cc":"0","sl":"nordstrom-the-north-face-aconcagua-down-jacket-2"}]